browserhand/__init__.py
browserhand/actions.py
browserhand/cli.py
browserhand/code_executor.py
browserhand/core.py
browserhand/extractors.py
browserhand/page_observer.py
browserhand/prompts.py
browserhand-0.1.2.dist-info/METADATA
browserhand-0.1.2.dist-info/WHEEL
browserhand-0.1.2.dist-info/entry_points.txt
browserhand-0.1.2.dist-info/top_level.txt
browserhand-0.1.2.dist-info/RECORD
