Metadata-Version: 2.2
Name: browserhand
Version: 0.1.2
Summary: AI-powered browser automation with natural language
Home-page: https://github.com/Dailogue/browserhand
Author: BrowserHand Team
Author-email: BrowserHand Team <hangerneil43@gmail.com>
Project-URL: Homepage, https://github.com/browserhand/browserhand
Requires-Python: >=3.7
Requires-Dist: playwright>=1.20.0
Requires-Dist: langchain-core>=0.0.1
Provides-Extra: dev
Requires-Dist: pytest>=6.0; extra == "dev"
Requires-Dist: black>=22.1.0; extra == "dev"
Requires-Dist: flake8>=4.0.1; extra == "dev"
Provides-Extra: azure
Requires-Dist: langchain-openai>=0.0.1; extra == "azure"
Provides-Extra: openai
Requires-Dist: langchain-openai>=0.0.1; extra == "openai"
Provides-Extra: anthropic
Requires-Dist: langchain-anthropic>=0.0.1; extra == "anthropic"
Provides-Extra: all
Requires-Dist: langchain-openai>=0.0.1; extra == "all"
Requires-Dist: langchain-anthropic>=0.0.1; extra == "all"
Dynamic: author
Dynamic: home-page
Dynamic: requires-python
